{
  "id": "khk-635",
  "type": "statute",
  "title": "SANAYİ VE TEKNOLOJİ BAKANLIĞININ ARAŞTIRMA, GELİŞTİRME, YENİLİKÇİLİK VE GİRİŞİMCİLİK FAALİYETLERİNİN KARŞILANMASI HAKKINDA KANUN HÜKMÜNDE KARARNAME",
  "title_en": "",
  "short_name": "SANAYİ VE TEKNOLOJİ BAKANLIĞININ ARAŞ...",
  "status": "in_force",
  "issued_date": "2011-06-08",
  "in_force_date": "2011-06-08",
  "url": "https://www.mevzuat.gov.tr/mevzuat?MevzuatNo=635&MevzuatTur=4&MevzuatTertip=5",
  "provisions": [
    {
      "provision_ref": "madde1",
      "section": "1",
      "title": "(Mülga: 2/7/2018-KHK-703/26md",
      "content": "Madde 1 - (Mülga: 2/7/2018-KHK-703/26md.)Görevler"
    },
    {
      "provision_ref": "madde2",
      "section": "2",
      "title": "(Mülga: 2/7/2018-KHK-703/26md",
      "content": "Madde 2 - (Mülga: 2/7/2018-KHK-703/26md.)İKİNCİ BÖLÜMBakanlık TeşkilatıTeşkilat"
    },
    {
      "provision_ref": "madde3",
      "section": "3",
      "title": "(Mülga: 2/7/2018-KHK-703/26md",
      "content": "Madde 3 - (Mülga: 2/7/2018-KHK-703/26md.)Bakan"
    },
    {
      "provision_ref": "madde4",
      "section": "4",
      "title": "(Mülga: 2/7/2018-KHK-703/26md",
      "content": "Madde 4 - (Mülga: 2/7/2018-KHK-703/26md.)Müsteşarve müsteşar yardımcıları"
    },
    {
      "provision_ref": "madde5",
      "section": "5",
      "title": "(Mülga: 2/7/2018-KHK-703/26md",
      "content": "Madde 5 - (Mülga: 2/7/2018-KHK-703/26md.)ÜÇÜNCÜ BÖLÜMHizmet BirimleriHizmet birimleri"
    },
    {
      "provision_ref": "madde6",
      "section": "6",
      "title": "(Mülga: 2/7/2018-KHK-703/26md",
      "content": "Madde 6 - (Mülga: 2/7/2018-KHK-703/26md.)Sanayi Genel Müdürlüğü"
    },
    {
      "provision_ref": "madde7",
      "section": "7",
      "title": "(Mülga: 2/7/2018-KHK-703/26md",
      "content": "Madde 7 - (Mülga: 2/7/2018-KHK-703/26md.)Projelerin Karşılanması [2]"
    },
    {
      "provision_ref": "madde8",
      "section": "8",
      "title": "(Değişik:30/5/2019-7176/20 md",
      "content": "Madde 8 - (Değişik:30/5/2019-7176/20 md.)(1) Sanayi ve TeknolojiBakanlığı tarafından sanayi alanındaki araştırma, geliştirme, yenilikçilik ve girişimcilikfaaliyetleri ile teknolojik gelişmeleri takip etmek, desteklemek ve teşvik etmekamacıyla sanayi kuruluşları, üniversiteler, araştırma merkezleri ve enstitüler ileişbirliği yaparak bu kurumların teknolojik araştırma ve geliştirmeye aktif katılımınısağlamak amacıyla hazırlanan programlara, projelere veya komite/komisyon/çalışmagruplarına ilişkin hizmetlerde 4/11/1981 tarihli ve 2547 sayılı Yükseköğretim Kanununun38 inci maddesine göre öğretim elemanları ve diğer kamu görevlileri ile kamu görevlisiolmayan alanında uzman diğer kişiler görevlendirilebilir. Bu şekilde görevlendirilenleriçin yapılacak harcamalar Bakanlık bütçesinden gerçekleştirilir. Bu kapsamda görevlendirilenöğretim elemanları ile kamu görevlisi olmayan alanında uzman diğer kişilere 2547sayılı Kanunun 38 inci maddesinde öngörülen aylık tutarın beş katını aşmamak kaydıyladiğer kanunlardaki düzenleme ve kısıtlamalara tabi olmaksızın her yıl Bakanlıkçabelirlenecek tutar üzerinden doğrudan görevlendirilen kişiye ödeme yapılır ve buödemeden yararlananlara ayrıca 10/2/1954 tarihli ve 6245 sayılı Harcırah Kanununagöre harcırah ödenmez.(2) Birinci fıkradabelirtilen amaçlarla yükseköğretim kurumlarına araştırma ve geliştirme projelerikarşılığı aktarılan hibe niteliğindeki tutarlar, ilgili idarelerin bütçelerine gelirkaydedilmeksizin proje adına açılacak özel hesaplarda izlenir. Yükseköğretim kurumlarıve vakıf üniversitelerine aktarılan tutarların harcanmasına ve muhasebeleştirilmesineilişkin hususlar Hazine ve Maliye Bakanlığının uygun görüşü alınmak suretiyle Bakanlıkçaçıkarılacak yönetmelikle belirlenir. Bu kapsamda yapılan harcamalar 10/12/2003 tarihlive 5018 sayılı Kamu Malî Yönetimi ve Kontrol Kanunu kapsamında denetlenir. Desteklenenprojelerde, proje süresiyle sınırlı olmak kaydıyla proje kapsamında görev yapanöğretim elemanlarına 15.000 gösterge rakamının, yükseköğretim kurumlarının teknikhizmetler sınıfında görev yapan personele ise 8.000 gösterge rakamının memur aylıklarınauygulanan katsayı ile çarpımı sonucu bulunacak tutarı geçmemek üzere proje sözleşmesindebelirlenen tutarlar üzerinden aylık ödeme yapılabilir. Memur ve diğer kamu görevlisiolmamak kaydıyla projede görev yapan diğer proje personeline proje sözleşmesindebelirlenen tutarlar üzerinden aylık ücret ödenir.(3) Bu Kanun Hükmünde Kararname ile 2547 sayılıKanuna göre görevlendirileceklerin asli görevlerine ait aylık, ücret, ödenek,her türlü zam ve tazminatları ile diğer mali ve sosyal hakları ödenmeye devamedilir. Bu madde kapsamında görevlendirilen öğretim elemanları, 2547 sayılıKanunun 58 inci maddesinde öngörülen ödemelerden aynı usul ve esaslarçerçevesinde yararlanır.Sanayi Bölgeleri Genel MüdürlüğüMADDE9- (Mülga: 2/7/2018-KHK-703/26 md.)Metroloji ve StandardizasyonGenel MüdürlüğüMADDE10- (Mülga: 2/7/2018-KHK-703/26 md.)Sanayi Ürünleri Güvenliğive Denetimi Genel MüdürlüğüMADDE11- (Mülga: 2/7/2018-KHK-703/26 md.)Verimlilik Genel Müdürlüğü"
    },
    {
      "provision_ref": "madde11_A",
      "section": "11/A",
      "title": "(Ek: 8/8/2011-KHK-649/4 md",
      "content": "Madde 11/A - (Ek: 8/8/2011-KHK-649/4 md.; Mülga:2/7/2018-KHK-703/26 md.)Avrupa Birliği ve Dış İlişkilerGenel MüdürlüğüMADDE12- (Mülga: 2/7/2018-KHK-703/26 md.)Rehberlik ve Teftiş BaşkanlığıMADDE13- (Mülga: 2/7/2018-KHK-703/26 md.)Strateji Geliştirme BaşkanlığıMADDE14- (Mülga: 2/7/2018-KHK-703/26 md.)Hukuk MüşavirliğiMADDE15- (Mülga: 2/7/2018-KHK-703/26 md.)PersonelDairesi BaşkanlığıMADDE16- (Mülga: 2/7/2018-KHK-703/26 md.)DestekHizmetleri Dairesi BaşkanlığıMADDE17- (Mülga: 2/7/2018-KHK-703/26 md.)Bilgi İşlem Dairesi BaşkanlığıMADDE18- (Mülga: 2/7/2018-KHK-703/26 md.)Basın ve Halkla İlişkilerMüşavirliğiMADDE19- (Mülga: 2/7/2018-KHK-703/26 md.)Özel Kalem MüdürlüğüMADDE20- (Mülga: 2/7/2018-KHK-703/26 md.)Bakanlık MüşavirleriMADDE21- (Mülga: 2/7/2018-KHK-703/26 md.)DÖRDÜNCÜBÖLÜMYurtdışıve Taşra Teşkilatı ile Şûra ve Çalışma Grupları [3]Yurtdışıve taşra teşkilatı [4]MADDE22- (Mülga: 2/7/2018-KHK-703/26 md.)Şûra ve çalışma grupları"
    },
    {
      "provision_ref": "madde23",
      "section": "23",
      "title": "(Mülga: 2/7/2018-KHK-703/26 md",
      "content": "Madde 23 - (Mülga: 2/7/2018-KHK-703/26 md.)BEŞİNCİBÖLÜMSorumlulukve YetkiYöneticilerin sorumlulukları"
    },
    {
      "provision_ref": "madde24",
      "section": "24",
      "title": "(Mülga: 2/7/2018-KHK-703/26 md",
      "content": "Madde 24 - (Mülga: 2/7/2018-KHK-703/26 md.)Yetkidevri"
    },
    {
      "provision_ref": "madde25",
      "section": "25",
      "title": "(Mülga: 2/7/2018-KHK-703/26 md",
      "content": "Madde 25 - (Mülga: 2/7/2018-KHK-703/26 md.)Koordinasyonve işbirliği"
    },
    {
      "provision_ref": "madde26",
      "section": "26",
      "title": "(Mülga: 2/7/2018-KHK-703/26 md",
      "content": "Madde 26 - (Mülga: 2/7/2018-KHK-703/26 md.)Düzenlemeyetkisi"
    },
    {
      "provision_ref": "madde27",
      "section": "27",
      "title": "(Mülga: 2/7/2018-KHK-703/26 md",
      "content": "Madde 27 - (Mülga: 2/7/2018-KHK-703/26 md.)Küçükve orta büyüklükteki işletmeler"
    },
    {
      "provision_ref": "madde28",
      "section": "28",
      "title": "(Mülga: 2/7/2018-KHK-703/26 md",
      "content": "Madde 28 - (Mülga: 2/7/2018-KHK-703/26 md.)ALTINCI BÖLÜMPersoneleİlişkin HükümlerAtamaMADDE29- (Mülga: 2/7/2018-KHK-703/26 md.)KadrolarMADDE30- (Mülga: 2/7/2018-KHK-703/26 md.)Sanayive Teknoloji Uzmanlığı [5]MADDE31- (Mülga: 2/7/2018-KHK-703/26 md.)EködemeMADDE32- (Mülga: 11/10/2011-KHK-666/1 md.)YEDİNCİBÖLÜMÇeşitliHükümlerAtıflar, değiştirilen veyürürlükten kaldırılan hükümlerMADDE33- (Mülga: 2/7/2018-KHK-703/26 md.)"
    },
    {
      "provision_ref": "ek_madde1",
      "chapter": "Ek Maddeler",
      "section": "E1",
      "title": "MADDE 1-",
      "content": "Ek Madde 1 - MADDE 1-"
    },
    {
      "provision_ref": "madde1",
      "section": "1",
      "title": "(Ek:25/12/2024-7537/22 md",
      "content": "Madde 1 - (Ek:25/12/2024-7537/22 md.)(1) Sanayi ve Teknoloji Bakanlığının görev ve yetkilerişunlardır:a) İlgili mevzuatta yer alan görevleri yapmak.b) Sanayi ürünlerine yönelik Bakanlığın görev alanına girenidari ve teknik düzenlemeleri hazırlamak, Türk standartlarından gerekligörülenleri zorunlu uygulamaya koymak, bunların uygulanmasını sağlamak,gerektiğinde denetlemek veya denetletmek.c) Görev ve yetkileri arasında yer alan destek programları veprojeleri ile ilgili görevlerini, belirleyeceği usul ve esaslar çerçevesindebağlı ve ilgili kuruluşlarına yaptırmak.ç) Sanayi işletmelerinin satın aldıkları sanayi ürünlerininsatış sonrası hizmetlerine yönelik ekonomik çıkarlarını koruyucu tedbirlerialmak ve gerekli düzenlemeleri yapmak, bu düzenlemelere yönelik denetimleriyapmak ya da yaptırmak.d) Türkiye’de bilimsel ve teknolojik araştırma, geliştirme,tasarım ve yenilikçilik faaliyetlerini ve girişimlerini teşvik etmek; bufaaliyetler sonucu ortaya çıkan ürünlerin patenti, yatırımı ve pazarlanmasıkonusunda gerçek ve tüzel kişilere destek vermek; bunlarla ilgili düzenlemeleryapmak, usul ve esasları belirlemek.e) Kamu kurum ve kuruluşları ile gerçek ve tüzel kişilerdenişletmelere ait yatırım, üretim, teşvik, mali durum, Ar-Ge, fikri ve sınaimülkiyet hakları, dış ticaret, istihdam ve işgücü, kurulu kapasite, fiilîüretim, enerji giderleri, verimlilik, dijitalleşme ve benzeri muhtelif ekonomikve kurumsal faaliyet bilgi ve verilerini, belirlenecek usul ve esaslardâhilinde almak, verilerin saklanması ve kullanılması için bilgi sistemi oluşturmakve yönetmek.f) İşletmelerin rekabet edebilirliğini artırmak amacıyla,üniversiteler, kamu kurum ve kuruluşları, sektörel birlikler, sivil toplumkuruluşları ve firmalar arasında teknolojik gelişim odaklı işbirliğini teşviketmek; kümelenme ve işbirliği mekanizmaları için destek programları hazırlamak,uygulamak ve izlemek; desteklere ilişkin usul ve esasları belirlemek.g) Ar-Ge ve yenilik faaliyetlerinin yaygın bir şekildegelişmesini sağlamak üzere, arayüz veya platform tabanlı destek ve teşvik modellerigeliştirmek, bunlara ilişkin usul ve esasları belirlemek ve uygulamak.ğ) (Ek:4/12/2025-7566/37 md.) İşletmelere; kapasitegeliştirme, ölçek ekonomisi oluşturma, verimlilik artırma, istihdamı koruma,piyasa koşullarındaki değişimlere karşı dayanıklılık kazandırma, rekabet gücünükoruma ve işletme sürdürülebilirliğini sağlama amaçlarıyla destek vermek ve budesteklere ilişkin usul ve esasları belirlemek."
    },
    {
      "provision_ref": "ek_madde2",
      "chapter": "Ek Maddeler",
      "section": "E2",
      "title": "MADDE 2-",
      "content": "Ek Madde 2 - MADDE 2-"
    },
    {
      "provision_ref": "madde2",
      "section": "2",
      "title": "(Ek:25/12/2024-7537/23 md",
      "content": "Madde 2 - (Ek:25/12/2024-7537/23 md.)(1) Sanayi ve Teknoloji Bakanlığı döner sermaye işletmesikurmaya yetkilidir. Döner sermaye işletmesine 500.000.000 (Beş yüz milyon) Türklirası sermaye tahsis edilmiştir. Tahsis edilen sermaye tutarı Cumhurbaşkanıkararıyla 5 katına kadar artırılabilir.(2) Döner sermaye; döner sermaye faaliyetlerinden elde edilecekkârlardan, bağış ve yardımlardan oluşur. Döner sermaye faaliyetlerinden eldeedilen kârlar, ödenmiş sermaye tahsis edilen tutara ulaşıncaya kadar sermayeyeeklenir. Ödenmiş sermaye tutarı, tahsis edilen sermaye tutarına ulaştıktansonra, yılsonu kârı hesap dönemini izleyen nisan ayının sonuna kadar genelbütçeye gelir kaydedilmek üzere ilgili muhasebe birimi hesabına yatırılır.Bağış ve yardımlar, tahsis edilen sermaye miktarı ile sınırlı olmaksızınsermayeye eklenir.(3) Sanayi ve Teknoloji Bakanlığı döner sermayesi; sanayi veteknoloji yatırımlarının, altyapı hizmetlerinin yürütülmesi, sanayi veteknoloji yatırımlarına ilişkin destek sağlanması, Ar-Ge ve yenilikfaaliyetleri, girişimcilik ekosisteminin geliştirilmesi, AB mevzuat ve uyumsüreçleri, bilişim, teknoloji, siber güvenlik faaliyetleri, dijitalleşme,dijital dönüşüm faaliyetleri, kamulaştırma dâhil kuruluş işlemlerininsağlanması, altyapının planlanması, altyapı proje ve tesislerinin, ayrıcaharitalandırma, danışmanlık ve benzeri işlerin yapılması/yaptırılması ile dönersermayenin işletilmesine ilişkin giderlerin karşılanması amacıyla kullanılır.(4) Sanayi ve Teknoloji Bakanlığının görev ve faaliyetalanları kapsamında, doğal afetler nedeniyle tahrip olan organize sanayibölgesi, endüstri bölgesi, teknoloji geliştirme bölgesi ve sanayi sitelerininihyası veya yeniden inşası amacıyla veya üçüncü fıkrada belirtilen iş vehizmetler ile sanayi ve teknoloji yatırımlarıyla doğrudan bağlantılı olmakkaydıyla yatırım projeleri ve bunların zorunlu altyapı hizmetlerinin yerinegetirilmesi amacıyla döner sermaye bütçesinden Sanayi ve Teknoloji Bakanınınonayıyla genel bütçeye kaynak aktarılabilir. Aktarılan bu tutarlar genelbütçeye gelir ve söz konusu tutarlar karşılığı yukarıda sayılan işlerin yapımıamacıyla Bakanlık bütçesine ödenek kaydedilir. Bu suretle ödenek kaydedilen tutarlardanyılı içinde harcanmayan kısımları aynı amaçlarla kullanılmak üzere ertesi yıladevretmeye Cumhurbaşkanı yetkilidir. Kaydedilen bu ödeneklerden yatırımprojeleri ile ilgili olanlar yılı yatırım programı ile ilişkilendirilir.(5) İşletmenin faaliyet alanları, gelirleri, giderleri,işleyişi ve denetimi ile diğer hususlar yönetmelikle düzenlenir.Düzenleyici işlemlerGEÇİCİ"
    },
    {
      "provision_ref": "madde1",
      "section": "1",
      "title": "(Mülga: 2/7/2018-KHK-703/26md",
      "content": "Madde 1 - (Mülga: 2/7/2018-KHK-703/26md.)Hakve yetkiler ile personelin devriGEÇİCİ"
    },
    {
      "provision_ref": "madde2",
      "section": "2",
      "title": "(Mülga: 2/7/2018-KHK-703/26md",
      "content": "Madde 2 - (Mülga: 2/7/2018-KHK-703/26md.)Mevcut personelGEÇİCİ"
    },
    {
      "provision_ref": "madde3",
      "section": "3",
      "title": "(Mülga: 2/7/2018-KHK-703/26md",
      "content": "Madde 3 - (Mülga: 2/7/2018-KHK-703/26md.)Kadro değişiklikleriGEÇİCİ"
    },
    {
      "provision_ref": "madde4",
      "section": "4",
      "title": "(Mülga: 2/7/2018-KHK-703/26md",
      "content": "Madde 4 - (Mülga: 2/7/2018-KHK-703/26md.)Mevcutişlerin yürütülmesiGEÇİCİ"
    },
    {
      "provision_ref": "madde5",
      "section": "5",
      "title": "(Mülga: 2/7/2018-KHK-703/26md",
      "content": "Madde 5 - (Mülga: 2/7/2018-KHK-703/26md.)MillîProdüktivite Merkezine ilişkin devir hükümleriGEÇİCİ"
    },
    {
      "provision_ref": "madde6",
      "section": "6",
      "title": "(Ek: 8/8/2011-KHK-649/6 md",
      "content": "Madde 6 - (Ek: 8/8/2011-KHK-649/6 md.; Mülga: 2/7/2018-KHK-703/26 md.)İdarihizmet sözleşmesi ile çalışan personelin memur kadrolarına atanmasıGEÇİCİ"
    },
    {
      "provision_ref": "madde7",
      "section": "7",
      "title": "(Ek: 4/7/2012-6353/59 md",
      "content": "Madde 7 - (Ek: 4/7/2012-6353/59 md.; Mülga:2/7/2018-KHK-703/26 md.)GEÇİCİ"
    },
    {
      "provision_ref": "madde8",
      "section": "8",
      "title": "(Ek:20/7/2025-7555/21 md",
      "content": "Madde 8 - (Ek:20/7/2025-7555/21 md.)(1)Türkiye Uzay Ajansı Başkanlığına uzay ve havacılık bilimi ve teknolojilerifaaliyetlerine ilişkin görevleri kapsamında yürüttüğü çalışmalara yönelik bütçeile tahsis edilen ödeneklerden ilgili hizmetleri gerçekleştirmek üzere SavunmaSanayii Destekleme Fonuna 31/12/2025 tarihine kadar ödeme yapmaya Sanayi veTeknoloji Bakanı yetkilidir.Yürürlük"
    },
    {
      "provision_ref": "madde34",
      "section": "34",
      "title": "Bu Kanun Hükmünde Kararname yayımıtarihinde yürürlüğe girer",
      "content": "Madde 34 - (1) Bu Kanun Hükmünde Kararname yayımıtarihinde yürürlüğe girer.YürütmeMADDE35- (1) Bu Kanun HükmündeKararname hükümlerini Bakanlar Kurulu yürütür.(I) SAYILICETVEL(Mülga:2/7/2018-KHK-703/26 md.)(…)635 SAYILI KHK’YE EK VE DEĞİŞİKLİK GETİRENMEVZUATIN VEYAANAYASA MAHKEMESİ İPTAL KARARLARININYÜRÜRLÜĞE GİRİŞ TARİHLERİNİ GÖSTERİR LİSTEDeğiştirenKanunun/ KHK’nin veya İptal Eden Anayasa Mahkemesi Kararının Numarası635 SayılıKHK’nin Değişen veya İptal Edilen MaddeleriYürürlüğeGiriş TarihiKHK/6492, 6, 11/A,Geçici Madde 2, Geçici Madde 3, Geçici Madde 6, (1) sayılı cetvel17/8/2011KHK/6663214/1/2012tarihinden geçerli olmak üzere 2/11/201163532, 3, 9,12, 22, Geçici Madde 712/7/2012649513, 312/8/2013Anayasa Mahkemesi’nin11/10/2012 tarihli ve E.:2011/84, K.:2012/151 sayılı Kararı.2, 10, 11,13, 31,26/7/2013Anayasa Mahkemesi’nin27/12/2012 tarihli veE.: 2011/139,K.: 2012/205 sayılı Kararı3210/10/201366762, 826/2/2016tarihini takip eden ay başında70332, 91/7/2017KHK/703KHK’nin Adı,1 ila 7, 8, 9 ila 33, Geçici Madde 1 ila Geçici Madde 7, Ek (I) sayılı cetvel24/6/2018tarihinde birlikte yapılan Türkiye Büyük Millet Meclisi ve Cumhurbaşkanlığı seçimlerisonucunda Cumhurbaşkanının andiçerek göreve başladığı tarihte (9/7/2018)7176KHK’nin Adı,89/7/2018tarihinden itibaren uygulanmak üzere yayımı tarihinde(12/6/2019)7537Ek Madde1, Ek Madde 221/12/2024 tarihinden itibaren geçerli olmak üzere yayımıtarihinde( 27/12/2024)7555GeçiciMadde 824/7/20257566Ek Madde119/12/2025[1]Bu KHK’nin Adı “Bilim, Sanayi ve Teknoloji Bakanlığının Teşkilat ve GörevleriHakkında Kanun Hükmünde Kararname” iken, 2/7/2018 tarihli ve 703 sayılı KHK’nin26 ncı maddesiyle metne işlendiği şekilde değiştirilmiştir. Daha sonra buKHK’nin Adı “Yükseköğretim Kurumlarının Araştırma ve Geliştirme Projelerinin KarşılanmasıHakkında Kanun Hükmünde Kararname” iken 30/5/2019 tarihli ve 7176 sayılıKanunun 20 nci maddesiyle metne işlendiği şekilde değiştirilmiştir.[2]Bu madde başlığı “Bilim ve Teknoloji Genel Müdürlüğü” iken, 2/7/2018 tarihli ve703 sayılı KHK’nin 26 ncı maddesiyle metne işlendiği şekilde değiştirilmiştir.[3]Bu bölüm başlığı “Taşra Teşkilatı, Şûra ve Çalışma Grupları” iken, 4/7/2012tarihli ve 6353 sayılı Kanunun 58 inci maddesiyle metne işlendiği şekilde değiştirilmiştir.[4]Bu madde başlığı “Taşra Teşkilatı” iken, 4/7/2012 tarihli ve 6353 sayılıKanunun 58 inci maddesiyle metne işlendiği şekilde değiştirilmiştir.[5]Bu madde başlığı” Sanayi ve Teknoloji Uzmanlığı” iken, 12/7/2013 tarihli ve6495 sayılı Kanunun 73 üncü maddesiyle metne işlendiği şekilde değiştirilmiştir.$(document).ready(function () {jQuery('table').each(function (cmp) {var parent = this.parentNode;var wrapper = document.createElement('div');parent.replaceChild(wrapper, this);wrapper.appendChild(this);this.parentElement.style.overflowX = 'auto';});if (window.location.search.indexOf(\"2709\") != -1 || window.location.search.indexOf(\"MevzuatTur=19\") != -1) {var tableCss = document.styleSheets[0].cssRules[2].style;tableCss.cssText = tableCss.cssText.replace(\"100%\", \"initial\");}//$('.tooltip').tooltipster();//replaceTable();//$(window).on('resize', function () {// replaceTable();//});//replaceTable();});//function replaceTable() {// //if (window.location.search.indexOf(\"MevzuatTur=19\") == -1) {// // var iframe = document.getElementsByTagName(\"td\");// // var value = $('body').width() - 10;// // for (var i = 0; i"
    }
  ],
  "definitions": []
}